benpay_merchant_api_sdk/__init__.py
benpay_merchant_api_sdk/client.py
benpay_merchant_api_sdk/param/__init__.py
benpay_merchant_api_sdk/param/benpay_merchant_param.py
benpay_merchant_api_sdk/utils.py
benpay_merchant_api_sdk-1.0.2.dist-info/METADATA
benpay_merchant_api_sdk-1.0.2.dist-info/WHEEL
benpay_merchant_api_sdk-1.0.2.dist-info/RECORD
