Metadata-Version: 2.3
Name: benpay_merchant_api_sdk
Version: 1.0.2
Summary: python sdk for benpay merchant
Author: yangbo
Author-email: yangbovin@gmail.com
Requires-Python: >=3.8.0,<4.0.0
Classifier: Programming Language :: Python :: 3
Classifier: Programming Language :: Python :: 3.8
Classifier: Programming Language :: Python :: 3.9
Classifier: Programming Language :: Python :: 3.10
Classifier: Programming Language :: Python :: 3.11
Classifier: Programming Language :: Python :: 3.12
Classifier: Programming Language :: Python :: 3.13
Requires-Dist: pycryptodome (==3.21.0)
Requires-Dist: requests (>=2.31.0,<3.0.0)
